essencia/__init__.py
essencia/descriptors/__init__.py
essencia/descriptors/base.py
essencia/descriptors/custom.py
essencia/deta/__init__.py
essencia/deta/base.py
essencia/enum/__init__.py
essencia/enum/integer.py
essencia/enum/string.py
essencia/enum/tuple.py
essencia/functions.py
essencia/models/__init__.py
essencia/models/abstract.py
essencia/models/assistant/__init__.py
essencia/models/assistant/model.py
essencia/models/business/__init__.py
essencia/models/business/model.py
essencia/models/care/__init__.py
essencia/models/care/model.py
essencia/models/client/__init__.py
essencia/models/client/model.py
essencia/models/provider/__init__.py
essencia/models/provider/model.py
essencia/settings.py
essencia.deta-0.1.3.dist-info/WHEEL
essencia.deta-0.1.3.dist-info/METADATA
essencia.deta-0.1.3.dist-info/RECORD
